pyllar/__init__.py
pyllar/errors.py
pyllar/finance.py
pyllar/flask_wrap.py
pyllar/util.py
pyllar/dashboard/__init__.py
pyllar/dashboard/analyzer.py
pyllar/dashboard/params.py
pyllar/dashboard/test_analyzer.py
pyllar-0.0.3.dist-info/LICENSE
pyllar-0.0.3.dist-info/METADATA
pyllar-0.0.3.dist-info/WHEEL
pyllar-0.0.3.dist-info/top_level.txt
pyllar-0.0.3.dist-info/RECORD
