Metadata-Version: 2.1
Name: pyllar
Version: 0.0.3
Summary: Tools to make webservices
Home-page: https://github.com/thorwhalen/newut/tree/master/pyllar
Author: Thor Whalen
License: mit
Platform: any
License-File: LICENSE
